examples/__init__.py
orion/__init__.py
orion/version.py
orion_search-0.0.1.dist-info/licenses/LICENSE
orion_search-0.0.1.dist-info/METADATA
orion_search-0.0.1.dist-info/WHEEL
orion_search-0.0.1.dist-info/top_level.txt
orion_search-0.0.1.dist-info/RECORD
